langdb_llm.py
adk_client-0.1.0.dist-info/licenses/LICENSE
adk_client-0.1.0.dist-info/METADATA
adk_client-0.1.0.dist-info/WHEEL
adk_client-0.1.0.dist-info/top_level.txt
adk_client-0.1.0.dist-info/RECORD
