Metadata-Version: 2.4
Name: adk-client
Version: 0.1.0
Summary: Add your description here
Requires-Python: >=3.13
License-File: LICENSE
Requires-Dist: google-adk>=1.3.0
Requires-Dist: pydantic>=2.11.7
Dynamic: license-file
